galaxy_parser/__init__.py
galaxy_parser/discerner.py
galaxy_parser/exceptions.py
galaxy_parser/galaxy.py
misp_galaxy_parser-0.1.5.data/scripts/query_galaxy.py
misp_galaxy_parser-0.1.5.data/scripts/update_cluster_tags.py
misp_galaxy_parser-0.1.5.dist-info/LICENSE
misp_galaxy_parser-0.1.5.dist-info/METADATA
misp_galaxy_parser-0.1.5.dist-info/NOTICE
misp_galaxy_parser-0.1.5.dist-info/WHEEL
misp_galaxy_parser-0.1.5.dist-info/top_level.txt
misp_galaxy_parser-0.1.5.dist-info/RECORD
