Metadata-Version: 2.1
Name: misp-galaxy-parser
Version: 0.1.5
Summary: Set of utilities to parse and use MISP galaxy clusters
Home-page: https://github.com/vmware-labs/galaxy-parser-for-misp/
Author: Stefano Ortolani
Project-URL: Bug Tracker, https://github.com/vmware-labs/galaxy-parser-for-misp/issues
Classifier: Development Status :: 3 - Alpha
Classifier: Intended Audience :: Developers
Classifier: License :: OSI Approved :: BSD License
Classifier: Programming Language :: Python :: 3
Classifier: Operating System :: OS Independent
Classifier: Topic :: Security
Classifier: Topic :: Software Development :: Libraries :: Python Modules
Requires-Python: >=3.9
License-File: LICENSE
License-File: NOTICE
Requires-Dist: requests
Requires-Dist: tqdm
Provides-Extra: misp
Requires-Dist: pymisp ; extra == 'misp'
